scancode_analyzer/__init__.py
scancode_analyzer/analyzer_plugin.py
scancode_analyzer/license_analyzer.py
scancode_analyzer/load_data.py
scancode_analyzer/nlp.py
scancode_analyzer/summary.py
scancode_analyzer-21.4.7.dist-info/METADATA
scancode_analyzer-21.4.7.dist-info/WHEEL
scancode_analyzer-21.4.7.dist-info/apache-2.0.LICENSE
scancode_analyzer-21.4.7.dist-info/entry_points.txt
scancode_analyzer-21.4.7.dist-info/top_level.txt
scancode_analyzer-21.4.7.dist-info/RECORD
