Metadata-Version: 2.1
Name: scancode-analyzer
Version: 21.4.7
Summary: A scancode-toolkit plugin to analyze scan results for License Detection Issues
Home-page: https://github.com/nexB/scancode-analyzer
Author: nexB. Inc. and others
Author-email: info@aboutcode.org
License: UNKNOWN
Keywords: - scancode,- license,- sca,- analysis,- classifiers,- nlp
Platform: UNKNOWN
Classifier: Development Status :: 4 - Beta
Classifier: Intended Audience :: Developers
Classifier: Programming Language :: Python :: 3
Classifier: Programming Language :: Python :: 3 :: Only
Classifier: Topic :: Software Development
Classifier: Topic :: Utilities
Requires-Python: >=3.6
Requires-Dist: scancode-toolkit (>=3.2)
Requires-Dist: attr
Requires-Dist: commoncode
Requires-Dist: plugincode
Provides-Extra: deep
Requires-Dist: pyyaml ; extra == 'deep'
Requires-Dist: pandas ; extra == 'deep'
Requires-Dist: tables ; extra == 'deep'
Requires-Dist: numpy (<1.19.0,>=1.16.0) ; extra == 'deep'
Requires-Dist: matplotlib ; extra == 'deep'
Requires-Dist: wordcloud ; extra == 'deep'
Requires-Dist: ernie ; extra == 'deep'
Requires-Dist: transformers (==2.4.1) ; extra == 'deep'
Requires-Dist: torch ; extra == 'deep'
Requires-Dist: psycopg2 ; extra == 'deep'
Provides-Extra: jupyter
Requires-Dist: jupyterlab ; extra == 'jupyter'
Provides-Extra: testing
Requires-Dist: pytest (>=6) ; extra == 'testing'
Requires-Dist: pytest-xdist (>=2) ; extra == 'testing'
